coloris/__init__.py
coloryi-10.0.9.dist-info/licenses/LICENSE
coloryi-10.0.9.dist-info/METADATA
coloryi-10.0.9.dist-info/WHEEL
coloryi-10.0.9.dist-info/top_level.txt
coloryi-10.0.9.dist-info/RECORD
